{
  "recommendedDrugs": [
    {
      "drug": "drug1",
      "substance": "substance1",
      "diseases": [
        "diseasesName1",
        "diseasesName2"
      ],
      "activeCompounds": [
        "compounds1",
        "compounds2"
      ]
    },
    {
      "drug": "drug2",
      "substance": "substance2",
      "diseases": [
        "diseasesName1",
        "diseasesName2"
      ],
      "activeCompounds": [
        "compounds1",
        "compounds2"
      ]
    }
  ],
  "otherRecommendations": [
    [
      {
        "drug": "drug1",
        "substance": "substance1",
        "diseases": [
          "diseasesName1",
          "diseasesName2"
        ],
        "activeCompounds": [
          "compounds1",
          "compounds2"
        ]
      },
      {
        "drug": "drug2",
        "substance": "substance2",
        "diseases": [
          "diseasesName1",
          "diseasesName2"
        ],
        "activeCompounds": [
          "compounds1",
          "compounds2"
        ]
      }
    ],
    [
      {
        "drug": "drug1",
        "substance": "substance1",
        "diseases": [
          "diseasesName1",
          "diseasesName2"
        ],
        "activeCompounds": [
          "compounds1",
          "compounds2"
        ]
      },
      {
        "drug": "drug2",
        "substance": "substance2",
        "diseases": [
          "diseasesName1",
          "diseasesName2"
        ],
        "activeCompounds": [
          "compounds1",
          "compounds2"
        ]
      }
    ]
  ]
}